{"data": {"2024-01-01": {"NZD": 1.0784805758}}}{"data": {"2024-01-02": {"NZD": 1.0825895556}}}{"data": {"2024-01-03": {"NZD": 1.0771281828}}}{"data": {"2024-01-04": {"NZD": 1.0765304562}}}{"data": {"2024-01-05": {"NZD": 1.0753161121}}}{"message": "API rate limit exceeded for 'quota'"}{"data": {"2024-01-07": {"NZD": 1.0748807612}}}{"message": "API rate limit exceeded for 'quota'"}{"message": "API rate limit exceeded for 'quota'"}{"message": "API rate limit exceeded for 'quota'"}{"data": {"2024-01-11": {"NZD": 1.0731170237}}}{"data": {"2024-03-08": {"NZD": 1.0727734476}}}{"data": {"2024-03-09": {"NZD": 1.0728661276}}}{"data": {"2024-03-10": {"NZD": 1.0721275329}}}{"data": {"2024-03-11": {"NZD": 1.0720533233}}}{"data": {"2024-01-01": {"NZD": 1.0784805758}}}{"data": {"2024-01-02": {"NZD": 1.0825895556}}}{"data": {"2024-01-03": {"NZD": 1.0771281828}}}{"data": {"2024-01-04": {"NZD": 1.0765304562}}}{"data": {"2024-01-05": {"NZD": 1.0753161121}}}{"message": "API rate limit exceeded for 'quota'"}{"data": {"2024-01-07": {"NZD": 1.0748807612}}}{"message": "API rate limit exceeded for 'quota'"}{"message": "API rate limit exceeded for 'quota'"}{"message": "API rate limit exceeded for 'quota'"}{"data": {"2024-01-11": {"NZD": 1.0731170237}}}{"data": {"2024-03-08": {"NZD": 1.0727734476}}}{"data": {"2024-03-09": {"NZD": 1.0728661276}}}{"data": {"2024-03-10": {"NZD": 1.0721275329}}}{"data": {"2024-03-11": {"NZD": 1.0720533233}}}